LICENSE
README.md
setup.py
src/__init__.py
src/signify/__init__.py
src/signify/signifying.py
src/signify/app/__init__.py
src/signify/app/aiding.py
src/signify/app/challenging.py
src/signify/app/clienting.py
src/signify/app/contacting.py
src/signify/app/coring.py
src/signify/app/credentialing.py
src/signify/app/ending.py
src/signify/app/escrowing.py
src/signify/app/grouping.py
src/signify/app/notifying.py
src/signify/app/cli/__init__.py
src/signify/app/cli/sigpy.py
src/signify/app/cli/commands/__init__.py
src/signify/app/cli/commands/status.py
src/signify/core/__init__.py
src/signify/core/authing.py
src/signify/core/httping.py
src/signify/core/keeping.py
src/signify/peer/__init__.py
src/signify/peer/exchanging.py
src/signifypy.egg-info/PKG-INFO
src/signifypy.egg-info/SOURCES.txt
src/signifypy.egg-info/dependency_links.txt
src/signifypy.egg-info/entry_points.txt
src/signifypy.egg-info/not-zip-safe
src/signifypy.egg-info/requires.txt
src/signifypy.egg-info/top_level.txt