Metadata-Version: 2.1
Name: signifypy
Version: 0.1.0rc1
Summary: Signify
Home-page: https://github.com/WebOfTrust/signifypy
Author: Philip S. Feairheller
Author-email: pfeairheller@gmail.com
License: Apache Software License 2.0
Project-URL: Documentation, https://signifypy.readthedocs.io/
Project-URL: Changelog, https://signifypy.readthedocs.io/en/latest/changelog.html
Project-URL: Issue Tracker, https://github.com/WebOfTrust/signifypy/issues
Platform: UNKNOWN
Classifier: Development Status :: 3 - Alpha
Classifier: Intended Audience :: Developers
Classifier: License :: OSI Approved :: Apache Software License
Classifier: Operating System :: Unix
Classifier: Operating System :: POSIX
Classifier: Operating System :: Microsoft :: Windows
Classifier: Programming Language :: Python :: 3.10
Classifier: Programming Language :: Python :: Implementation :: CPython
Classifier: Topic :: Utilities
Requires-Python: >=3.10.4
License-File: LICENSE
